zip_read_yaml/__init__.py
zip_read_yaml/zip_read.py
zip_read_yaml-0.1.dist-info/METADATA
zip_read_yaml-0.1.dist-info/WHEEL
zip_read_yaml-0.1.dist-info/top_level.txt
zip_read_yaml-0.1.dist-info/RECORD
