Metadata-Version: 2.1
Name: zip-read-yaml
Version: 0.1
Summary: Test the read of yaml files from zip folders
Home-page: https://github.com/h-swathi-shenoy/build-pkg-exercise
Author: hswathishenoy
Author-email: hswathishenoy@gmail.com
License: MIT
Platform: UNKNOWN
